batch_resize/__init__.py
batch_resize/__main__.py
batch_resize-1.0.1.dist-info/METADATA
batch_resize-1.0.1.dist-info/WHEEL
batch_resize-1.0.1.dist-info/top_level.txt
batch_resize-1.0.1.dist-info/RECORD
